README.md
setup.py
soham_thesis.egg-info/PKG-INFO
soham_thesis.egg-info/SOURCES.txt
soham_thesis.egg-info/dependency_links.txt
soham_thesis.egg-info/top_level.txt
thesis_figures/__init__.py