Metadata-Version: 2.1
Name: soham-thesis
Version: 0.0.1
Summary: Data, Analysis, and Plotting Code for PhD thesis
Author: soham_mukhopadhyay
Author-email: Soham.Mukhopadhyay@ist.ac.at
License: UNKNOWN
Platform: UNKNOWN
